henon2midi/__init__.py
henon2midi/__main__.py
henon2midi/ascii_art.py
henon2midi/base.py
henon2midi/cli.py
henon2midi/henon_equations.py
henon2midi/henon_midi_generator.py
henon2midi/math.py
henon2midi/midi.py
henon2midi-0.0.1.dist-info/LICENSE
henon2midi-0.0.1.dist-info/METADATA
henon2midi-0.0.1.dist-info/WHEEL
henon2midi-0.0.1.dist-info/entry_points.txt
henon2midi-0.0.1.dist-info/top_level.txt
henon2midi-0.0.1.dist-info/RECORD
