Metadata-Version: 2.1
Name: henon2midi
Version: 0.0.1
Summary: This application generates midi bifurcation diagrams generated from generated logistic map data.
Author: Josh Symes
Classifier: Programming Language :: Python :: 3
Classifier: License :: OSI Approved :: MIT License
Classifier: Operating System :: OS Independent
License-File: LICENSE
Requires-Dist: mido
Requires-Dist: click
Requires-Dist: python-rtmidi
Requires-Dist: colorama
Provides-Extra: test
Requires-Dist: pytest ; extra == 'test'
Requires-Dist: pytest-cov ; extra == 'test'
Requires-Dist: pytest-mock ; extra == 'test'
Requires-Dist: coverage ; extra == 'test'
Requires-Dist: flake8 ; extra == 'test'
Requires-Dist: black ; extra == 'test'
Requires-Dist: isort ; extra == 'test'
Requires-Dist: mypy ; extra == 'test'
Requires-Dist: types-setuptools ; extra == 'test'
Requires-Dist: pre-commit ; extra == 'test'
